appsrvdeployer/__init__.py
appsrvdeployer/__main__.py
appsrvdeployer/modules/__init__.py
appsrvdeployer/modules/ftp.py
appsrvdeployer/modules/logger.py
appsrvdeployer/modules/provisioning.py
appsrvdeployer/modules/utils.py
appservice_deployer-0.0.5.dist-info/WHEEL
appservice_deployer-0.0.5.dist-info/METADATA
appservice_deployer-0.0.5.dist-info/license_files/LICENSE
appservice_deployer-0.0.5.dist-info/RECORD
