Metadata-Version: 2.1
Name: appservice-deployer
Version: v0.0.5
Summary: Azure App Service file deployer
License: MIT
Author-email: Fabio Felici <fabio.felici96c@gmail.com>
Requires-Python: >=3.8
Project-URL: Bug Tracker, https://github.com/rhslack/appservice-deployer/issues
Project-URL: homepage, https://github.com/rhslack/appservice-deployer
